muvinai/__init__.py
muvinai/objects/__init__.py
muvinai/objects/boletaObject.py
muvinai/objects/clientObject.py
muvinai/service/__init__.py
muvinai/service/boleta.py
muvinai/service/brand.py
muvinai/service/card.py
muvinai/service/cliente.py
muvinai/service/corporativo.py
muvinai/service/merchant.py
muvinai/service/muviBase.py
muvinai/service/plan.py
muvinai/service/sede.py
muvinai/utilities/__init__.py
muvinai/utilities/afip.py
muvinai/utilities/authorization.py
muvinai/utilities/dates.py
muvinai/utilities/db_operations.py
muvinai/utilities/facturacion_afip.py
muvinai/utilities/format.py
muvinai/utilities/init_creds.py
muvinai/utilities/mail_sender.py
muvinai/utilities/members.py
muvinai/utilities/mercadopago_ops.py
muvinai/utilities/payments.py
muvinai/utilities/projections.py
muvinai/utilities/sportaccess.py
muvinai/utilities/webflow.py
muvinai-0.2.69.dist-info/METADATA
muvinai-0.2.69.dist-info/WHEEL
muvinai-0.2.69.dist-info/top_level.txt
muvinai-0.2.69.dist-info/RECORD
