Metadata-Version: 2.1
Name: muvinai
Version: 0.2.69
Summary: Utilities for muvinai developers
Author: muvinai
Classifier: Programming Language :: Python :: 3
Classifier: Operating System :: OS Independent
Requires-Python: >=3.6
Requires-Dist: gspread
Requires-Dist: cryptography
Requires-Dist: python-dotenv
Requires-Dist: mercadopago
Requires-Dist: pymongo[srv]
Requires-Dist: iso8601
Requires-Dist: pyopenssl
Requires-Dist: reportlab
Requires-Dist: qrcode
Requires-Dist: PyPDF2 ==2.12.1
Requires-Dist: zeep
Requires-Dist: xmltodict
Requires-Dist: python-dateutil
Requires-Dist: babel
Requires-Dist: numpy
Requires-Dist: muvisdk
Requires-Dist: deepdiff
